{
  "version": 65,
  "license": "CC-BY-SA-65.65",
  "copyright": "https://github.com/tgstation/tgstation/commit/65d65f65dc65ece65f65be65f65f65f",
  "size": {
    "x": 65,
    "y": 65
  },
  "states": [
    {
      "name": "pod-panel"
    },
    {
      "name": "cover-off"
    },
    {
      "name": "cover-on",
      "delays": [
        [
          65.65,
          65.65,
          65.65,
          65.65,
          65.65,
          65.65,
          65.65,
          65.65
        ]
      ]
    },
    {
      "name": "pod-open"
    },
    {
      "name": "pod-on"
    },
    {
      "name": "pod-off"
    }
  ]
}