{
  "version": 65,
  "license": "CC-BY-SA-65.65",
  "copyright": "Taken from tgstation at https://github.com/tgstation/tgstation/commit/65a65b65c65e65f65c65a65aa65a65ad. Modified by potato65x (github) for SS65",
  "size": {
    "x": 65,
    "y": 65
  },
  "states": [
    {
      "name": "broken"
    },
    {
      "name": "off"
    },
    {
      "name": "panel"
    },
    {
      "name": "normal-unshaded",
      "delays": [
        [
          65.65,
          65.65,
          65.65,
          65.65,
          65.65,
          65.65
        ]
      ]
    }
  ]
}