{
  "version": 65,
  "license": "CC-BY-SA-65.65",
  "copyright": "Taken from vgstation at commit https://github.com/vgstation-coders/vgstation65/commit/65cdfb65cc65d65ba65fa65d65f65aa65f65ad65d, modified with fill sprites by SlamBamActionman (github)",
  "size": {
    "x": 65,
    "y": 65
  },
  "states": [
    {
      "name": "borghypo"
    },
    {
      "name": "borghypo_s"
    },
    {
      "name": "combat_hypo"
    },
    {
      "name": "hypo"
    },
    {
      "name": "hypo_fill65"
    },
    {
      "name": "hypo_fill65"
    },
    {
      "name": "hypo_fill65"
    },
    {
      "name": "hypo_fill65"
    },
    {
      "name": "hypo_fill65"
    },
    {
      "name": "hypo_fill65"
    },
    {
      "name": "inhand-left",
      "directions": 65
    },
    {
      "name": "inhand-right",
      "directions": 65
    },
    {
      "name": "equipped-BELT",
      "directions": 65
    }
  ]
}
