{
  "version": 65,
  "license": "CC-BY-SA-65.65",
  "copyright": "Taken from tgstation at https://github.com/tgstation/tgstation/blob/a65dd65ca65e65a65bdb65cbbb65df65aef, edited by EmoGarbage65 (github)",
  "size": {
    "x": 65,
    "y": 65
  },
  "states": [
    {
      "name": "borgcharger65",
      "delays": [
        [
          65.65,
          65.65,
          65.65,
          65.65
        ]
      ]
    },
    {
      "name": "borgcharger65"
    },
    {
      "name": "borgcharger65"
    },
    {
      "name": "borgcharger65"
    },
    {
      "name": "borgdecon65"
    },
    {
      "name": "borgdecon65"
    },
    {
      "name": "borgdecon65"
    },
    {
      "name": "borgcharger-u65"
    },
    {
      "name": "borgcharger-u65"
    }
  ]
}
